MySQLCorsair/__init__.py
MySQLCorsair/__main__.py
MySQLCorsair/cli_helpers.py
MySQLCorsair/command_helpers.py
MySQLCorsair/commands.py
MySQLCorsair/config_helpers.py
MySQLCorsair/data_pulling_helpers.py
MySQLCorsair/database_structure.py
MySQLCorsair/foreign_key.py
MySQLCorsair/main.py
MySQLCorsair/models.py
MySQLCorsair/sql_query_helpers.py
MySQLCorsair/views.py
MySQLCorsair/data_slices/__init__.py
MySQLCorsair/data_slices/edge.py
MySQLCorsair/data_slices/graph.py
MySQLCorsair/data_slices/network_x_graph.py
MySQLCorsair/data_slices/node.py
mysql_corsair-0.0.13.dist-info/DESCRIPTION.rst
mysql_corsair-0.0.13.dist-info/METADATA
mysql_corsair-0.0.13.dist-info/RECORD
mysql_corsair-0.0.13.dist-info/WHEEL
mysql_corsair-0.0.13.dist-info/entry_points.txt
mysql_corsair-0.0.13.dist-info/metadata.json
mysql_corsair-0.0.13.dist-info/top_level.txt
