Metadata-Version: 2.0
Name: mysql-corsair
Version: 0.0.13
Summary: Tool to move slices of data from one MySQL store to another
Home-page: UNKNOWN
Author: Andre Kuney
Author-email: andre.kuney@newsela.com
License: UNKNOWN
Platform: UNKNOWN
Classifier: Development Status :: 3 - Alpha
Classifier: Intended Audience :: Developers
Classifier: Topic :: Database
Classifier: License :: OSI Approved :: MIT License
Classifier: Programming Language :: Python :: 2.7
Classifier: Programming Language :: Python :: 3
Classifier: Programming Language :: Python :: 3.2
Classifier: Programming Language :: Python :: 3.3
Classifier: Programming Language :: Python :: 3.4
Requires-Dist: mysqlclient (==1.3.7)
Requires-Dist: networkx (==1.11)
